{"basePath":"","info":{"title":"API-DOCS"},"paths":{"/nodes":{"get":{"description":"Pings AMOC nodes from master node.","parameters":[],"produces":["application/json"],"responses":{"200":{"description":"response object","schema":{"properties":{"nodes":{"description":"nodeName: up | down","type":"object"}},"required":["nodes"],"type":"object"}}},"tags":["node"]}},"/scenarios":{"get":{"description":"Gets list of available scenarios","parameters":[],"produces":["application/json"],"responses":{"200":{"description":"response object","schema":{"properties":{"scenarios":{"description":"Scenario names","items":{"type":"string"},"type":"array"}},"required":["scenarios"],"type":"object"}}},"tags":["scenarios"]}},"/scenarios/upload":{"put":{"consumes":["text/plain"],"description":"Uploads new scenario (add '--upload-file scenario.erl' flag to the curl command)","parameters":[],"produces":["application/json"],"responses":{"200":{"description":"response object","schema":{"properties":{"compile":{"description":"ok | Errors","type":"string"}},"required":["compile"],"type":"object"}}},"tags":["upload"]}},"/scenarios/{id}":{"get":{"description":"Gets scenario status","parameters":[{"description":"Scenario id","in":"path","name":"id","required":true,"type":"string"}],"produces":["application/json"],"responses":{"200":{"description":"response object","schema":{"properties":{"scenario_status":{"description":"loaded | running | finished","type":"string"}},"required":["scenario_status"],"type":"object"}}},"tags":["scenario"]},"patch":{"description":"Starts scenario","parameters":[{"description":"Scenario id","in":"path","name":"id","required":true,"type":"string"},{"description":"request body (as json)","in":"body","name":"request body","required":true,"schema":{"properties":{"users":{"description":"Number of users to start","type":"integer"}},"required":["users"],"type":"object"}}],"produces":["application/json"],"responses":{"200":{"description":"response object","schema":{"properties":{"scenario":{"description":"started | wrong_json","type":"string"}},"required":["scenario"],"type":"object"}}},"tags":["scenario"]}},"/status":{"get":{"description":"Gets AMOC status, whether it is running or not.","parameters":[],"produces":["application/json"],"responses":{"200":{"description":"response object","schema":{"properties":{"node_status":{"description":"up | down","type":"string"}},"required":["node_status"],"type":"object"}}},"tags":["status"]}}},"swagger":"2.0"}